<?xml version="1.0" encoding="UTF-8"?>
<export version="D">
  <design>
    <source>C:\Users\hooke\Documents\Workspace\Drone\Kicad Projects\transmitter\transmitter.sch</source>
    <date>2/20/2022 19:46:14</date>
    <tool>Eeschema (5.1.10)-1</tool>
    <sheet number="1" name="/" tstamps="/">
      <title_block>
        <title/>
        <company/>
        <rev/>
        <date/>
        <source>transmitter.sch</source>
        <comment number="1" value=""/>
        <comment number="2" value=""/>
        <comment number="3" value=""/>
        <comment number="4" value=""/>
      </title_block>
    </sheet>
  </design>
  <components>
    <comp ref="R4">
      <value>120R</value>
      <footprint>Resistor_SMD:R_0402_1005Metric</footprint>
      <datasheet>https://www.vishay.com/docs/20035/dcrcwe3.pdf</datasheet>
      <fields>
        <field name="Description">RES SMD 120 OHM 5% 1/16W 0402</field>
        <field name="Part Number">CRCW0402120RJNED</field>
        <field name="Tolerance">5%</field>
      </fields>
      <libsource lib="Device" part="R_Small" description="Resistor, small symbol"/>
      <sheetpath names="/" tstamps="/"/>
      <tstamp>60191760</tstamp>
    </comp>
    <comp ref="R5">
      <value>120R</value>
      <footprint>Resistor_SMD:R_0402_1005Metric</footprint>
      <datasheet>https://www.vishay.com/docs/20035/dcrcwe3.pdf</datasheet>
      <fields>
        <field name="Description">RES SMD 120 OHM 5% 1/16W 0402</field>
        <field name="Part Number">CRCW0402120RJNED</field>
        <field name="Tolerance">5%</field>
      </fields>
      <libsource lib="Device" part="R_Small" description="Resistor, small symbol"/>
      <sheetpath names="/" tstamps="/"/>
      <tstamp>60192AD1</tstamp>
    </comp>
    <comp ref="C13">
      <value>10pF</value>
      <footprint>Capacitor_SMD:C_0402_1005Metric</footprint>
      <datasheet>https://product.tdk.com/en/system/files?file=dam/doc/product/capacitor/ceramic/mlcc/catalog/mlcc_commercial_general_en.pdf</datasheet>
      <fields>
        <field name="Description">CAP CER 10PF 50V C0G 0402</field>
        <field name="Part Number">C1005C0G1H100D</field>
        <field name="Tolerance">0.05%</field>
        <field name="Voltage">50V</field>
      </fields>
      <libsource lib="Device" part="C_Small" description="Unpolarized capacitor, small symbol"/>
      <sheetpath names="/" tstamps="/"/>
      <tstamp>601938B7</tstamp>
    </comp>
    <comp ref="C12">
      <value>10pF</value>
      <footprint>Capacitor_SMD:C_0402_1005Metric</footprint>
      <datasheet>https://product.tdk.com/en/system/files?file=dam/doc/product/capacitor/ceramic/mlcc/catalog/mlcc_commercial_general_en.pdf</datasheet>
      <fields>
        <field name="Description">CAP CER 10PF 50V C0G 0402</field>
        <field name="Part Number">C1005C0G1H100D</field>
        <field name="Tolerance">0.05%</field>
        <field name="Voltage">50V</field>
      </fields>
      <libsource lib="Device" part="C_Small" description="Unpolarized capacitor, small symbol"/>
      <sheetpath names="/" tstamps="/"/>
      <tstamp>6019431A</tstamp>
    </comp>
    <comp ref="R6">
      <value>120R</value>
      <footprint>Resistor_SMD:R_0402_1005Metric</footprint>
      <datasheet>https://www.vishay.com/docs/20035/dcrcwe3.pdf</datasheet>
      <fields>
        <field name="Description">RES SMD 120 OHM 5% 1/16W 0402</field>
        <field name="Part Number">CRCW0402120RJNED</field>
        <field name="Tolerance">5%</field>
      </fields>
      <libsource lib="Device" part="R_Small" description="Resistor, small symbol"/>
      <sheetpath names="/" tstamps="/"/>
      <tstamp>6019A467</tstamp>
    </comp>
    <comp ref="C11">
      <value>10pF</value>
      <footprint>Capacitor_SMD:C_0402_1005Metric</footprint>
      <datasheet>https://product.tdk.com/en/system/files?file=dam/doc/product/capacitor/ceramic/mlcc/catalog/mlcc_commercial_general_en.pdf</datasheet>
      <fields>
        <field name="Description">CAP CER 10PF 50V C0G 0402</field>
        <field name="Part Number">C1005C0G1H100D</field>
        <field name="Tolerance">0.05%</field>
        <field name="Voltage">50V</field>
      </fields>
      <libsource lib="Device" part="C_Small" description="Unpolarized capacitor, small symbol"/>
      <sheetpath names="/" tstamps="/"/>
      <tstamp>6019AEA5</tstamp>
    </comp>
    <comp ref="C3">
      <value>0.01uF</value>
      <footprint>Capacitor_SMD:C_0402_1005Metric</footprint>
      <datasheet>https://www.murata.com/-/media/webrenewal/support/library/catalog/products/capacitor/ceramiccapacitor/c02e.ashx?la=en-us&amp;cvid=20210120024548000000</datasheet>
      <fields>
        <field name="Description">CAP CER 10000PF 16V X7R 0402</field>
        <field name="Part Number">GRM155R71C103K</field>
        <field name="Tolerance">10%</field>
        <field name="Voltage">16V</field>
      </fields>
      <libsource lib="Device" part="C_Small" description="Unpolarized capacitor, small symbol"/>
      <sheetpath names="/" tstamps="/"/>
      <tstamp>601A9FA0</tstamp>
    </comp>
    <comp ref="C1">
      <value>100pF</value>
      <footprint>Capacitor_SMD:C_0402_1005Metric</footprint>
      <datasheet>https://product.tdk.com/en/system/files?file=dam/doc/product/capacitor/ceramic/mlcc/catalog/mlcc_commercial_general_en.pdf</datasheet>
      <fields>
        <field name="Description">CAP CER 100PF 50V C0G 0402</field>
        <field name="Part Number">C1005C0G1H101K</field>
        <field name="Tolerance">5%</field>
        <field name="Voltage">50V</field>
      </fields>
      <libsource lib="Device" part="C_Small" description="Unpolarized capacitor, small symbol"/>
      <sheetpath names="/" tstamps="/"/>
      <tstamp>601A959C</tstamp>
    </comp>
    <comp ref="C21">
      <value>0.01uF</value>
      <footprint>Capacitor_SMD:C_0402_1005Metric</footprint>
      <datasheet>https://www.murata.com/-/media/webrenewal/support/library/catalog/products/capacitor/ceramiccapacitor/c02e.ashx?la=en-us&amp;cvid=20210120024548000000</datasheet>
      <fields>
        <field name="Description">CAP CER 10000PF 16V X7R 0402</field>
        <field name="Part Number">GRM155R71C103K</field>
        <field name="Tolerance">10%</field>
        <field name="Voltage">16V</field>
      </fields>
      <libsource lib="Device" part="C_Small" description="Unpolarized capacitor, small symbol"/>
      <sheetpath names="/" tstamps="/"/>
      <tstamp>601B6138</tstamp>
    </comp>
    <comp ref="C6">
      <value>100pF</value>
      <footprint>Capacitor_SMD:C_0402_1005Metric</footprint>
      <datasheet>https://product.tdk.com/en/system/files?file=dam/doc/product/capacitor/ceramic/mlcc/catalog/mlcc_commercial_general_en.pdf</datasheet>
      <fields>
        <field name="Description">CAP CER 100PF 50V C0G 0402</field>
        <field name="Part Number">C1005C0G1H101K</field>
        <field name="Tolerance">5%</field>
        <field name="Voltage">50V</field>
      </fields>
      <libsource lib="Device" part="C_Small" description="Unpolarized capacitor, small symbol"/>
      <sheetpath names="/" tstamps="/"/>
      <tstamp>601F9174</tstamp>
    </comp>
    <comp ref="C8">
      <value>0.01uF</value>
      <footprint>Capacitor_SMD:C_0402_1005Metric</footprint>
      <datasheet>https://www.murata.com/-/media/webrenewal/support/library/catalog/products/capacitor/ceramiccapacitor/c02e.ashx?la=en-us&amp;cvid=20210120024548000000</datasheet>
      <fields>
        <field name="Description">CAP CER 10000PF 16V X7R 0402</field>
        <field name="Part Number">GRM155R71C103K</field>
        <field name="Tolerance">10%</field>
        <field name="Voltage">16V</field>
      </fields>
      <libsource lib="Device" part="C_Small" description="Unpolarized capacitor, small symbol"/>
      <sheetpath names="/" tstamps="/"/>
      <tstamp>601F95C9</tstamp>
    </comp>
    <comp ref="C14">
      <value>100pF</value>
      <footprint>Capacitor_SMD:C_0402_1005Metric</footprint>
      <datasheet>https://product.tdk.com/en/system/files?file=dam/doc/product/capacitor/ceramic/mlcc/catalog/mlcc_commercial_general_en.pdf</datasheet>
      <fields>
        <field name="Description">CAP CER 100PF 50V C0G 0402</field>
        <field name="Part Number">C1005C0G1H101K</field>
        <field name="Tolerance">5%</field>
        <field name="Voltage">50V</field>
      </fields>
      <libsource lib="Device" part="C_Small" description="Unpolarized capacitor, small symbol"/>
      <sheetpath names="/" tstamps="/"/>
      <tstamp>6020E40B</tstamp>
    </comp>
    <comp ref="C15">
      <value>0.01uF</value>
      <footprint>Capacitor_SMD:C_0402_1005Metric</footprint>
      <datasheet>https://www.murata.com/-/media/webrenewal/support/library/catalog/products/capacitor/ceramiccapacitor/c02e.ashx?la=en-us&amp;cvid=20210120024548000000</datasheet>
      <fields>
        <field name="Description">CAP CER 10000PF 16V X7R 0402</field>
        <field name="Part Number">GRM155R71C103K</field>
        <field name="Tolerance">10%</field>
        <field name="Voltage">16V</field>
      </fields>
      <libsource lib="Device" part="C_Small" description="Unpolarized capacitor, small symbol"/>
      <sheetpath names="/" tstamps="/"/>
      <tstamp>6020E9AF</tstamp>
    </comp>
    <comp ref="U2">
      <value>MAX2870</value>
      <footprint>Package_DFN_QFN:TQFN-32-1EP_5x5mm_P0.5mm_EP3.1x3.1mm_ThermalVias</footprint>
      <datasheet>https://datasheets.maximintegrated.com/en/ds/MAX2870.pdf</datasheet>
      <fields>
        <field name="Description">RF FRACT INTR N SYNTH VCO 32TQFN</field>
        <field name="Part Number">MAX2870ETJ+</field>
      </fields>
      <libsource lib="Timer_PLL" part="MAX2870" description="23.5MHz to 6000MHz Fractional/Integer-N Synthesizer/VCO"/>
      <sheetpath names="/" tstamps="/"/>
      <tstamp>6018E9F9</tstamp>
    </comp>
    <comp ref="C27">
      <value>1.0uF</value>
      <footprint>Capacitor_SMD:C_0402_1005Metric</footprint>
      <datasheet>https://search.murata.co.jp/Ceramy/image/img/A01X/G101/ENG/GRM155C81A105KA12-01.pdf</datasheet>
      <fields>
        <field name="Description">CAP CER 1UF 10V X6S 0402</field>
        <field name="Part Number">GRM155C81A105K</field>
        <field name="Tolerance">10%</field>
        <field name="Voltage">10V</field>
      </fields>
      <libsource lib="Device" part="C_Small" description="Unpolarized capacitor, small symbol"/>
      <sheetpath names="/" tstamps="/"/>
      <tstamp>6021578B</tstamp>
    </comp>
    <comp ref="C28">
      <value>1.0uF</value>
      <footprint>Capacitor_SMD:C_0402_1005Metric</footprint>
      <datasheet>https://search.murata.co.jp/Ceramy/image/img/A01X/G101/ENG/GRM155C81A105KA12-01.pdf</datasheet>
      <fields>
        <field name="Description">CAP CER 1UF 10V X6S 0402</field>
        <field name="Part Number">GRM155C81A105K</field>
        <field name="Tolerance">10%</field>
        <field name="Voltage">10V</field>
      </fields>
      <libsource lib="Device" part="C_Small" description="Unpolarized capacitor, small symbol"/>
      <sheetpath names="/" tstamps="/"/>
      <tstamp>60216763</tstamp>
    </comp>
    <comp ref="R29">
      <value>5.1k</value>
      <footprint>Resistor_SMD:R_0402_1005Metric</footprint>
      <datasheet>https://www.vishay.com/docs/28773/crcwce3.pdf</datasheet>
      <fields>
        <field name="Description">RES 5.1K OHM 1% 1/16W 0402</field>
        <field name="Part Number">CRCW04025K10FKEDC</field>
        <field name="Tolerance">1%</field>
      </fields>
      <libsource lib="Device" part="R_Small" description="Resistor, small symbol"/>
      <sheetpath names="/" tstamps="/"/>
      <tstamp>6021D60B</tstamp>
    </comp>
    <comp ref="C29">
      <value>1.0uF</value>
      <footprint>Capacitor_SMD:C_0402_1005Metric</footprint>
      <datasheet>https://search.murata.co.jp/Ceramy/image/img/A01X/G101/ENG/GRM155C81A105KA12-01.pdf</datasheet>
      <fields>
        <field name="Description">CAP CER 1UF 10V X6S 0402</field>
        <field name="Part Number">GRM155C81A105K</field>
        <field name="Tolerance">10%</field>
        <field name="Voltage">10V</field>
      </fields>
      <libsource lib="Device" part="C_Small" description="Unpolarized capacitor, small symbol"/>
      <sheetpath names="/" tstamps="/"/>
      <tstamp>6022F742</tstamp>
    </comp>
    <comp ref="C17">
      <value>100pF</value>
      <footprint>Capacitor_SMD:C_0402_1005Metric</footprint>
      <datasheet>https://product.tdk.com/en/system/files?file=dam/doc/product/capacitor/ceramic/mlcc/catalog/mlcc_commercial_general_en.pdf</datasheet>
      <fields>
        <field name="Description">CAP CER 100PF 50V C0G 0402</field>
        <field name="Part Number">C1005C0G1H101K</field>
        <field name="Tolerance">5%</field>
        <field name="Voltage">50V</field>
      </fields>
      <libsource lib="Device" part="C_Small" description="Unpolarized capacitor, small symbol"/>
      <sheetpath names="/" tstamps="/"/>
      <tstamp>60233299</tstamp>
    </comp>
    <comp ref="C18">
      <value>0.01uF</value>
      <footprint>Capacitor_SMD:C_0402_1005Metric</footprint>
      <datasheet>https://www.murata.com/-/media/webrenewal/support/library/catalog/products/capacitor/ceramiccapacitor/c02e.ashx?la=en-us&amp;cvid=20210120024548000000</datasheet>
      <fields>
        <field name="Description">CAP CER 10000PF 16V X7R 0402</field>
        <field name="Part Number">GRM155R71C103K</field>
        <field name="Tolerance">10%</field>
        <field name="Voltage">16V</field>
      </fields>
      <libsource lib="Device" part="C_Small" description="Unpolarized capacitor, small symbol"/>
      <sheetpath names="/" tstamps="/"/>
      <tstamp>602339C9</tstamp>
    </comp>
    <comp ref="C22">
      <value>100pF</value>
      <footprint>Capacitor_SMD:C_0402_1005Metric</footprint>
      <datasheet>https://product.tdk.com/en/system/files?file=dam/doc/product/capacitor/ceramic/mlcc/catalog/mlcc_commercial_general_en.pdf</datasheet>
      <fields>
        <field name="Description">CAP CER 100PF 50V C0G 0402</field>
        <field name="Part Number">C1005C0G1H101K</field>
        <field name="Tolerance">5%</field>
        <field name="Voltage">50V</field>
      </fields>
      <libsource lib="Device" part="C_Small" description="Unpolarized capacitor, small symbol"/>
      <sheetpath names="/" tstamps="/"/>
      <tstamp>60244889</tstamp>
    </comp>
    <comp ref="C23">
      <value>100pF</value>
      <footprint>Capacitor_SMD:C_0402_1005Metric</footprint>
      <datasheet>https://product.tdk.com/en/system/files?file=dam/doc/product/capacitor/ceramic/mlcc/catalog/mlcc_commercial_general_en.pdf</datasheet>
      <fields>
        <field name="Description">CAP CER 100PF 50V C0G 0402</field>
        <field name="Part Number">C1005C0G1H101K</field>
        <field name="Tolerance">5%</field>
        <field name="Voltage">50V</field>
      </fields>
      <libsource lib="Device" part="C_Small" description="Unpolarized capacitor, small symbol"/>
      <sheetpath names="/" tstamps="/"/>
      <tstamp>60245823</tstamp>
    </comp>
    <comp ref="C24">
      <value>100pF</value>
      <footprint>Capacitor_SMD:C_0402_1005Metric</footprint>
      <datasheet>https://product.tdk.com/en/system/files?file=dam/doc/product/capacitor/ceramic/mlcc/catalog/mlcc_commercial_general_en.pdf</datasheet>
      <fields>
        <field name="Description">CAP CER 100PF 50V C0G 0402</field>
        <field name="Part Number">C1005C0G1H101K</field>
        <field name="Tolerance">5%</field>
        <field name="Voltage">50V</field>
      </fields>
      <libsource lib="Device" part="C_Small" description="Unpolarized capacitor, small symbol"/>
      <sheetpath names="/" tstamps="/"/>
      <tstamp>60245A51</tstamp>
    </comp>
    <comp ref="C25">
      <value>100pF</value>
      <footprint>Capacitor_SMD:C_0402_1005Metric</footprint>
      <datasheet>https://product.tdk.com/en/system/files?file=dam/doc/product/capacitor/ceramic/mlcc/catalog/mlcc_commercial_general_en.pdf</datasheet>
      <fields>
        <field name="Description">CAP CER 100PF 50V C0G 0402</field>
        <field name="Part Number">C1005C0G1H101K</field>
        <field name="Tolerance">5%</field>
        <field name="Voltage">50V</field>
      </fields>
      <libsource lib="Device" part="C_Small" description="Unpolarized capacitor, small symbol"/>
      <sheetpath names="/" tstamps="/"/>
      <tstamp>60245BD8</tstamp>
    </comp>
    <comp ref="R23">
      <value>27nH</value>
      <footprint>Inductor_SMD:L_0402_1005Metric</footprint>
      <datasheet>https://search.murata.co.jp/Ceramy/image/img/P02/JELF243C-0007.pdf</datasheet>
      <fields>
        <field name="Description">FIXED IND 27NH 70MA 3.1 OHM SMD</field>
        <field name="Part Number">LQP15MN27NG02</field>
        <field name="Tolerance">2%</field>
      </fields>
      <libsource lib="Device" part="R_Small" description="Resistor, small symbol"/>
      <sheetpath names="/" tstamps="/"/>
      <tstamp>60246182</tstamp>
    </comp>
    <comp ref="R22">
      <value>27nH</value>
      <footprint>Inductor_SMD:L_0402_1005Metric</footprint>
      <datasheet>https://search.murata.co.jp/Ceramy/image/img/P02/JELF243C-0007.pdf</datasheet>
      <fields>
        <field name="Description">FIXED IND 27NH 70MA 3.1 OHM SMD</field>
        <field name="Part Number">LQP15MN27NG02</field>
        <field name="Tolerance">2%</field>
      </fields>
      <libsource lib="Device" part="R_Small" description="Resistor, small symbol"/>
      <sheetpath names="/" tstamps="/"/>
      <tstamp>602479D7</tstamp>
    </comp>
    <comp ref="C26">
      <value>0.01uF</value>
      <footprint>Capacitor_SMD:C_0402_1005Metric</footprint>
      <datasheet>https://www.murata.com/-/media/webrenewal/support/library/catalog/products/capacitor/ceramiccapacitor/c02e.ashx?la=en-us&amp;cvid=20210120024548000000</datasheet>
      <fields>
        <field name="Description">CAP CER 10000PF 16V X7R 0402</field>
        <field name="Part Number">GRM155R71C103K</field>
        <field name="Tolerance">10%</field>
        <field name="Voltage">16V</field>
      </fields>
      <libsource lib="Device" part="C_Small" description="Unpolarized capacitor, small symbol"/>
      <sheetpath names="/" tstamps="/"/>
      <tstamp>6024F6AA</tstamp>
    </comp>
    <comp ref="R16">
      <value>27nH</value>
      <footprint>Inductor_SMD:L_0402_1005Metric</footprint>
      <datasheet>https://search.murata.co.jp/Ceramy/image/img/P02/JELF243C-0007.pdf</datasheet>
      <fields>
        <field name="Description">FIXED IND 27NH 70MA 3.1 OHM SMD</field>
        <field name="Part Number">LQP15MN27NG02</field>
        <field name="Tolerance">2%</field>
      </fields>
      <libsource lib="Device" part="R_Small" description="Resistor, small symbol"/>
      <sheetpath names="/" tstamps="/"/>
      <tstamp>60259DFA</tstamp>
    </comp>
    <comp ref="R17">
      <value>27nH</value>
      <footprint>Inductor_SMD:L_0402_1005Metric</footprint>
      <datasheet>https://search.murata.co.jp/Ceramy/image/img/P02/JELF243C-0007.pdf</datasheet>
      <fields>
        <field name="Description">FIXED IND 27NH 70MA 3.1 OHM SMD</field>
        <field name="Part Number">LQP15MN27NG02</field>
        <field name="Tolerance">2%</field>
      </fields>
      <libsource lib="Device" part="R_Small" description="Resistor, small symbol"/>
      <sheetpath names="/" tstamps="/"/>
      <tstamp>6025A71F</tstamp>
    </comp>
    <comp ref="C19">
      <value>0.01uF</value>
      <footprint>Capacitor_SMD:C_0402_1005Metric</footprint>
      <datasheet>https://www.murata.com/-/media/webrenewal/support/library/catalog/products/capacitor/ceramiccapacitor/c02e.ashx?la=en-us&amp;cvid=20210120024548000000</datasheet>
      <fields>
        <field name="Description">CAP CER 10000PF 16V X7R 0402</field>
        <field name="Part Number">GRM155R71C103K</field>
        <field name="Tolerance">10%</field>
        <field name="Voltage">16V</field>
      </fields>
      <libsource lib="Device" part="C_Small" description="Unpolarized capacitor, small symbol"/>
      <sheetpath names="/" tstamps="/"/>
      <tstamp>60261E51</tstamp>
    </comp>
    <comp ref="R12">
      <value>18R</value>
      <footprint>Resistor_SMD:R_0402_1005Metric</footprint>
      <datasheet>https://www.vishay.com/docs/20035/dcrcwe3.pdf</datasheet>
      <fields>
        <field name="Description">RES SMD 18 OHM 1% 1/16W 0402</field>
        <field name="Part Number">CRCW040218R0FKED</field>
        <field name="Tolerance">1%</field>
      </fields>
      <libsource lib="Device" part="R_Small" description="Resistor, small symbol"/>
      <sheetpath names="/" tstamps="/"/>
      <tstamp>60280A63</tstamp>
    </comp>
    <comp ref="R14">
      <value>300R</value>
      <footprint>Resistor_SMD:R_0402_1005Metric</footprint>
      <datasheet>https://www.vishay.com/docs/28773/crcwce3.pdf</datasheet>
      <fields>
        <field name="Description">RES 300 OHM 1% 1/16W 0402</field>
        <field name="Part Number">CRCW0402300RFKEDC</field>
        <field name="Tolerance">1%</field>
      </fields>
      <libsource lib="Device" part="R_Small" description="Resistor, small symbol"/>
      <sheetpath names="/" tstamps="/"/>
      <tstamp>602817FB</tstamp>
    </comp>
    <comp ref="R9">
      <value>300R</value>
      <footprint>Resistor_SMD:R_0402_1005Metric</footprint>
      <datasheet>https://www.vishay.com/docs/28773/crcwce3.pdf</datasheet>
      <fields>
        <field name="Description">RES 300 OHM 1% 1/16W 0402</field>
        <field name="Part Number">CRCW0402300RFKEDC</field>
        <field name="Tolerance">1%</field>
      </fields>
      <libsource lib="Device" part="R_Small" description="Resistor, small symbol"/>
      <sheetpath names="/" tstamps="/"/>
      <tstamp>60281C46</tstamp>
    </comp>
    <comp ref="R13">
      <value>18R</value>
      <footprint>Resistor_SMD:R_0402_1005Metric</footprint>
      <datasheet>https://www.vishay.com/docs/20035/dcrcwe3.pdf</datasheet>
      <fields>
        <field name="Description">RES SMD 18 OHM 1% 1/16W 0402</field>
        <field name="Part Number">CRCW040218R0FKED</field>
        <field name="Tolerance">1%</field>
      </fields>
      <libsource lib="Device" part="R_Small" description="Resistor, small symbol"/>
      <sheetpath names="/" tstamps="/"/>
      <tstamp>60291B3B</tstamp>
    </comp>
    <comp ref="R15">
      <value>300R</value>
      <footprint>Resistor_SMD:R_0402_1005Metric</footprint>
      <datasheet>https://www.vishay.com/docs/28773/crcwce3.pdf</datasheet>
      <fields>
        <field name="Description">RES 300 OHM 1% 1/16W 0402</field>
        <field name="Part Number">CRCW0402300RFKEDC</field>
        <field name="Tolerance">1%</field>
      </fields>
      <libsource lib="Device" part="R_Small" description="Resistor, small symbol"/>
      <sheetpath names="/" tstamps="/"/>
      <tstamp>60291B45</tstamp>
    </comp>
    <comp ref="R10">
      <value>300R</value>
      <footprint>Resistor_SMD:R_0402_1005Metric</footprint>
      <datasheet>https://www.vishay.com/docs/28773/crcwce3.pdf</datasheet>
      <fields>
        <field name="Description">RES 300 OHM 1% 1/16W 0402</field>
        <field name="Part Number">CRCW0402300RFKEDC</field>
        <field name="Tolerance">1%</field>
      </fields>
      <libsource lib="Device" part="R_Small" description="Resistor, small symbol"/>
      <sheetpath names="/" tstamps="/"/>
      <tstamp>60291B4F</tstamp>
    </comp>
    <comp ref="R27">
      <value>18R</value>
      <footprint>Resistor_SMD:R_0402_1005Metric</footprint>
      <datasheet>https://www.vishay.com/docs/20035/dcrcwe3.pdf</datasheet>
      <fields>
        <field name="Description">RES SMD 18 OHM 1% 1/16W 0402</field>
        <field name="Part Number">CRCW040218R0FKED</field>
        <field name="Tolerance">1%</field>
      </fields>
      <libsource lib="Device" part="R_Small" description="Resistor, small symbol"/>
      <sheetpath names="/" tstamps="/"/>
      <tstamp>6029CCED</tstamp>
    </comp>
    <comp ref="R30">
      <value>300R</value>
      <footprint>Resistor_SMD:R_0402_1005Metric</footprint>
      <datasheet>https://www.vishay.com/docs/28773/crcwce3.pdf</datasheet>
      <fields>
        <field name="Description">RES 300 OHM 1% 1/16W 0402</field>
        <field name="Part Number">CRCW0402300RFKEDC</field>
        <field name="Tolerance">1%</field>
      </fields>
      <libsource lib="Device" part="R_Small" description="Resistor, small symbol"/>
      <sheetpath names="/" tstamps="/"/>
      <tstamp>6029CCF7</tstamp>
    </comp>
    <comp ref="R24">
      <value>300R</value>
      <footprint>Resistor_SMD:R_0402_1005Metric</footprint>
      <datasheet>https://www.vishay.com/docs/28773/crcwce3.pdf</datasheet>
      <fields>
        <field name="Description">RES 300 OHM 1% 1/16W 0402</field>
        <field name="Part Number">CRCW0402300RFKEDC</field>
        <field name="Tolerance">1%</field>
      </fields>
      <libsource lib="Device" part="R_Small" description="Resistor, small symbol"/>
      <sheetpath names="/" tstamps="/"/>
      <tstamp>6029CD01</tstamp>
    </comp>
    <comp ref="R28">
      <value>18R</value>
      <footprint>Resistor_SMD:R_0402_1005Metric</footprint>
      <datasheet>https://www.vishay.com/docs/20035/dcrcwe3.pdf</datasheet>
      <fields>
        <field name="Description">RES SMD 18 OHM 1% 1/16W 0402</field>
        <field name="Part Number">CRCW040218R0FKED</field>
        <field name="Tolerance">1%</field>
      </fields>
      <libsource lib="Device" part="R_Small" description="Resistor, small symbol"/>
      <sheetpath names="/" tstamps="/"/>
      <tstamp>6029CD25</tstamp>
    </comp>
    <comp ref="R31">
      <value>300R</value>
      <footprint>Resistor_SMD:R_0402_1005Metric</footprint>
      <datasheet>https://www.vishay.com/docs/28773/crcwce3.pdf</datasheet>
      <fields>
        <field name="Description">RES 300 OHM 1% 1/16W 0402</field>
        <field name="Part Number">CRCW0402300RFKEDC</field>
        <field name="Tolerance">1%</field>
      </fields>
      <libsource lib="Device" part="R_Small" description="Resistor, small symbol"/>
      <sheetpath names="/" tstamps="/"/>
      <tstamp>6029CD2F</tstamp>
    </comp>
    <comp ref="R25">
      <value>300R</value>
      <footprint>Resistor_SMD:R_0402_1005Metric</footprint>
      <datasheet>https://www.vishay.com/docs/28773/crcwce3.pdf</datasheet>
      <fields>
        <field name="Description">RES 300 OHM 1% 1/16W 0402</field>
        <field name="Part Number">CRCW0402300RFKEDC</field>
        <field name="Tolerance">1%</field>
      </fields>
      <libsource lib="Device" part="R_Small" description="Resistor, small symbol"/>
      <sheetpath names="/" tstamps="/"/>
      <tstamp>6029CD39</tstamp>
    </comp>
    <comp ref="J5">
      <value>RFOUTBN</value>
      <footprint>Connector_Coaxial:SMA_Amphenol_132289_EdgeMount</footprint>
      <datasheet>https://s3-us-west-2.amazonaws.com/catsy.582/132289.pdf</datasheet>
      <fields>
        <field name="Description">CONN SMA RCPT STR 50OHM EDGE MNT</field>
        <field name="Part Number">132289</field>
      </fields>
      <libsource lib="Connector" part="Conn_Coaxial" description="coaxial connector (BNC, SMA, SMB, SMC, Cinch/RCA, ...)"/>
      <sheetpath names="/" tstamps="/"/>
      <tstamp>602B77E8</tstamp>
    </comp>
    <comp ref="J6">
      <value>RFOUTBP</value>
      <footprint>Connector_Coaxial:SMA_Amphenol_132289_EdgeMount</footprint>
      <datasheet>https://s3-us-west-2.amazonaws.com/catsy.582/132289.pdf</datasheet>
      <fields>
        <field name="Description">CONN SMA RCPT STR 50OHM EDGE MNT</field>
        <field name="Part Number">132289</field>
      </fields>
      <libsource lib="Connector" part="Conn_Coaxial" description="coaxial connector (BNC, SMA, SMB, SMC, Cinch/RCA, ...)"/>
      <sheetpath names="/" tstamps="/"/>
      <tstamp>602B9396</tstamp>
    </comp>
    <comp ref="J1">
      <value>RFOUTAP</value>
      <footprint>Connector_Coaxial:SMA_Amphenol_132289_EdgeMount</footprint>
      <datasheet>https://s3-us-west-2.amazonaws.com/catsy.582/132289.pdf</datasheet>
      <fields>
        <field name="Description">CONN SMA RCPT STR 50OHM EDGE MNT</field>
        <field name="Part Number">132289</field>
      </fields>
      <libsource lib="Connector" part="Conn_Coaxial" description="coaxial connector (BNC, SMA, SMB, SMC, Cinch/RCA, ...)"/>
      <sheetpath names="/" tstamps="/"/>
      <tstamp>602C8017</tstamp>
    </comp>
    <comp ref="J2">
      <value>RFOUTAN</value>
      <footprint>Connector_Coaxial:SMA_Amphenol_132289_EdgeMount</footprint>
      <datasheet>https://s3-us-west-2.amazonaws.com/catsy.582/132289.pdf</datasheet>
      <fields>
        <field name="Description">CONN SMA RCPT STR 50OHM EDGE MNT</field>
        <field name="Part Number">132289</field>
      </fields>
      <libsource lib="Connector" part="Conn_Coaxial" description="coaxial connector (BNC, SMA, SMB, SMC, Cinch/RCA, ...)"/>
      <sheetpath names="/" tstamps="/"/>
      <tstamp>602C99AF</tstamp>
    </comp>
    <comp ref="U3">
      <value>MAX8559ETAAA</value>
      <footprint>Package_DFN_QFN:TDFN-8-1EP_3x3mm_P0.65mm_EP1.5x2.3mm</footprint>
      <datasheet>https://datasheets.maximintegrated.com/en/ds/MAX8559.pdf</datasheet>
      <fields>
        <field name="Description">IC REG LINEAR 1.8V/1.8V 8TDFN</field>
        <field name="Part Number">MAX8559ETA22+T</field>
      </fields>
      <libsource lib="Regulator_Linear" part="MAX8559" description="Dual, 300mA, Low-Noise Linear Regulator with Independent Shutdown"/>
      <sheetpath names="/" tstamps="/"/>
      <tstamp>60314EB9</tstamp>
    </comp>
    <comp ref="R34">
      <value>10k</value>
      <footprint>Resistor_SMD:R_0402_1005Metric</footprint>
      <datasheet>https://www.vishay.com/docs/20035/dcrcwe3.pdf</datasheet>
      <fields>
        <field name="Description">RES SMD 10K OHM 1% 1/16W 0402</field>
        <field name="Part Number">CRCW040210K0FKED</field>
        <field name="Tolerance">1%</field>
      </fields>
      <libsource lib="Device" part="R_Small" description="Resistor, small symbol"/>
      <sheetpath names="/" tstamps="/"/>
      <tstamp>603171DE</tstamp>
    </comp>
    <comp ref="R35">
      <value>10k</value>
      <footprint>Resistor_SMD:R_0402_1005Metric</footprint>
      <datasheet>https://www.vishay.com/docs/20035/dcrcwe3.pdf</datasheet>
      <fields>
        <field name="Description">RES SMD 10K OHM 1% 1/16W 0402</field>
        <field name="Part Number">CRCW040210K0FKED</field>
        <field name="Tolerance">1%</field>
      </fields>
      <libsource lib="Device" part="R_Small" description="Resistor, small symbol"/>
      <sheetpath names="/" tstamps="/"/>
      <tstamp>6031D067</tstamp>
    </comp>
    <comp ref="C32">
      <value>0.01uF</value>
      <footprint>Capacitor_SMD:C_0402_1005Metric</footprint>
      <datasheet>https://www.murata.com/-/media/webrenewal/support/library/catalog/products/capacitor/ceramiccapacitor/c02e.ashx?la=en-us&amp;cvid=20210120024548000000</datasheet>
      <fields>
        <field name="Description">CAP CER 10000PF 16V X7R 0402</field>
        <field name="Part Number">GRM155R71C103K</field>
        <field name="Tolerance">10%</field>
        <field name="Voltage">16V</field>
      </fields>
      <libsource lib="Device" part="C_Small" description="Unpolarized capacitor, small symbol"/>
      <sheetpath names="/" tstamps="/"/>
      <tstamp>6033F096</tstamp>
    </comp>
    <comp ref="C34">
      <value>2.2uF</value>
      <footprint>Capacitor_SMD:C_0201_0603Metric</footprint>
      <datasheet>https://www.murata.com/-/media/webrenewal/support/library/catalog/products/capacitor/ceramiccapacitor/c02e.ashx?la=en-us&amp;cvid=20210120024548000000</datasheet>
      <fields>
        <field name="Description">CAP CER 2.2UF 10V X5R 0201</field>
        <field name="Part Number">GRM033R61A225K</field>
        <field name="Tolerance">10%</field>
        <field name="Voltage">10V</field>
      </fields>
      <libsource lib="Device" part="C_Small" description="Unpolarized capacitor, small symbol"/>
      <sheetpath names="/" tstamps="/"/>
      <tstamp>60384234</tstamp>
    </comp>
    <comp ref="R37">
      <value>5.1k</value>
      <footprint>Resistor_SMD:R_0402_1005Metric</footprint>
      <datasheet>https://www.vishay.com/docs/28773/crcwce3.pdf</datasheet>
      <fields>
        <field name="Description">RES 5.1K OHM 1% 1/16W 0402</field>
        <field name="Part Number">CRCW04025K10FKEDC</field>
        <field name="Tolerance">1%</field>
      </fields>
      <libsource lib="Device" part="R_Small" description="Resistor, small symbol"/>
      <sheetpath names="/" tstamps="/"/>
      <tstamp>6039141C</tstamp>
    </comp>
    <comp ref="D3">
      <value>LED</value>
      <footprint>Diode_SMD:D_0603_1608Metric</footprint>
      <datasheet>https://fscdn.rohm.com/en/products/databook/datasheet/opto/led/chip_mono/sml-d12x8_d13x8-e.pdf</datasheet>
      <fields>
        <field name="Description">LED GREEN DIFFUSED 0603 SMD</field>
        <field name="Part Number">SML-D12P8WT86</field>
      </fields>
      <libsource lib="Device" part="LED" description="Light emitting diode"/>
      <sheetpath names="/" tstamps="/"/>
      <tstamp>6039F15F</tstamp>
    </comp>
    <comp ref="C38">
      <value>0.1uF</value>
      <footprint>Capacitor_SMD:C_0805_2012Metric</footprint>
      <datasheet>https://search.murata.co.jp/Ceramy/image/img/A01X/G101/ENG/GRM155R71E104KE14-01.pdf</datasheet>
      <fields>
        <field name="Description">CAP CER 0.1UF 25V X7R 0402</field>
        <field name="Part Number">GRM155R71E104K</field>
        <field name="Tolerance">10%</field>
        <field name="Voltage">16V</field>
      </fields>
      <libsource lib="Device" part="C_Small" description="Unpolarized capacitor, small symbol"/>
      <sheetpath names="/" tstamps="/"/>
      <tstamp>603AD3F0</tstamp>
    </comp>
    <comp ref="C36">
      <value>4.7uF</value>
      <footprint>Capacitor_SMD:C_0805_2012Metric</footprint>
      <datasheet>https://www.murata.com/-/media/webrenewal/support/library/catalog/products/capacitor/ceramiccapacitor/c02e.ashx?la=en-us&amp;cvid=20210120024548000000</datasheet>
      <fields>
        <field name="Description">CAP CER 4.7UF 16V X5R 0805</field>
        <field name="Part Number">GRM219R61C475K</field>
        <field name="Tolerance">10%</field>
        <field name="Voltage">16V</field>
      </fields>
      <libsource lib="Device" part="C_Small" description="Unpolarized capacitor, small symbol"/>
      <sheetpath names="/" tstamps="/"/>
      <tstamp>603ACD4B</tstamp>
    </comp>
    <comp ref="C33">
      <value>2.2uF</value>
      <footprint>Capacitor_SMD:C_0201_0603Metric</footprint>
      <datasheet>https://www.murata.com/-/media/webrenewal/support/library/catalog/products/capacitor/ceramiccapacitor/c02e.ashx?la=en-us&amp;cvid=20210120024548000000</datasheet>
      <fields>
        <field name="Description">CAP CER 2.2UF 10V X5R 0201</field>
        <field name="Part Number">GRM033R61A225K</field>
        <field name="Tolerance">10%</field>
        <field name="Voltage">10V</field>
      </fields>
      <libsource lib="Device" part="C_Small" description="Unpolarized capacitor, small symbol"/>
      <sheetpath names="/" tstamps="/"/>
      <tstamp>603EAB11</tstamp>
    </comp>
    <comp ref="R36">
      <value>5.1k</value>
      <footprint>Resistor_SMD:R_0402_1005Metric</footprint>
      <datasheet>https://www.vishay.com/docs/28773/crcwce3.pdf</datasheet>
      <fields>
        <field name="Description">RES 5.1K OHM 1% 1/16W 0402</field>
        <field name="Part Number">CRCW04025K10FKEDC</field>
        <field name="Tolerance">1%</field>
      </fields>
      <libsource lib="Device" part="R_Small" description="Resistor, small symbol"/>
      <sheetpath names="/" tstamps="/"/>
      <tstamp>603EAB20</tstamp>
    </comp>
    <comp ref="D2">
      <value>LED</value>
      <footprint>Diode_SMD:D_0603_1608Metric</footprint>
      <datasheet>https://fscdn.rohm.com/en/products/databook/datasheet/opto/led/chip_mono/sml-d12x8_d13x8-e.pdf</datasheet>
      <fields>
        <field name="Description">LED GREEN DIFFUSED 0603 SMD</field>
        <field name="Part Number">SML-D12P8WT86</field>
      </fields>
      <libsource lib="Device" part="LED" description="Light emitting diode"/>
      <sheetpath names="/" tstamps="/"/>
      <tstamp>603EAB28</tstamp>
    </comp>
    <comp ref="C37">
      <value>0.1uF</value>
      <footprint>Capacitor_SMD:C_0805_2012Metric</footprint>
      <datasheet>https://search.murata.co.jp/Ceramy/image/img/A01X/G101/ENG/GRM155R71E104KE14-01.pdf</datasheet>
      <fields>
        <field name="Description">CAP CER 0.1UF 25V X7R 0402</field>
        <field name="Part Number">GRM155R71E104K</field>
        <field name="Tolerance">10%</field>
        <field name="Voltage">16V</field>
      </fields>
      <libsource lib="Device" part="C_Small" description="Unpolarized capacitor, small symbol"/>
      <sheetpath names="/" tstamps="/"/>
      <tstamp>603EAB37</tstamp>
    </comp>
    <comp ref="C35">
      <value>4.7uF</value>
      <footprint>Capacitor_SMD:C_0805_2012Metric</footprint>
      <datasheet>https://www.murata.com/-/media/webrenewal/support/library/catalog/products/capacitor/ceramiccapacitor/c02e.ashx?la=en-us&amp;cvid=20210120024548000000</datasheet>
      <fields>
        <field name="Description">CAP CER 4.7UF 16V X5R 0805</field>
        <field name="Part Number">GRM219R61C475K</field>
        <field name="Tolerance">10%</field>
        <field name="Voltage">16V</field>
      </fields>
      <libsource lib="Device" part="C_Small" description="Unpolarized capacitor, small symbol"/>
      <sheetpath names="/" tstamps="/"/>
      <tstamp>603EAB41</tstamp>
    </comp>
    <comp ref="C10">
      <value>0.012uF</value>
      <footprint>Capacitor_SMD:C_0805_2012Metric</footprint>
      <datasheet>https://www.murata.com/-/media/webrenewal/support/library/catalog/products/capacitor/ceramiccapacitor/c02e.ashx?la=en-us&amp;cvid=20210120024548000000</datasheet>
      <fields>
        <field name="Description">CAP CER 100PF 50V C0G 0402</field>
        <field name="Part Number">GRM155R71C123K</field>
        <field name="Tolerance">10%</field>
        <field name="Voltage">50V</field>
      </fields>
      <libsource lib="Device" part="C_Small" description="Unpolarized capacitor, small symbol"/>
      <sheetpath names="/" tstamps="/"/>
      <tstamp>605373CE</tstamp>
    </comp>
    <comp ref="C5">
      <value>0.1uF</value>
      <footprint>Capacitor_SMD:C_0805_2012Metric</footprint>
      <datasheet>https://search.murata.co.jp/Ceramy/image/img/A01X/G101/ENG/GRM155R71E104KE14-01.pdf</datasheet>
      <fields>
        <field name="Description">CAP CER 0.1UF 25V X7R 0402</field>
        <field name="Part Number">GRM155R71E104K</field>
        <field name="Tolerance">10%</field>
        <field name="Voltage">16V</field>
      </fields>
      <libsource lib="Device" part="C_Small" description="Unpolarized capacitor, small symbol"/>
      <sheetpath names="/" tstamps="/"/>
      <tstamp>605386B3</tstamp>
    </comp>
    <comp ref="R2">
      <value>30.1R</value>
      <footprint>Resistor_SMD:R_0402_1005Metric</footprint>
      <datasheet>https://www.vishay.com/docs/20008/dcrcw.pdf</datasheet>
      <fields>
        <field name="Description">0402\600WIND,30.1 Ohms,1%</field>
        <field name="Part Number">CRCW040230R1FKTD</field>
        <field name="Tolerance">1%</field>
      </fields>
      <libsource lib="Device" part="R_Small" description="Resistor, small symbol"/>
      <sheetpath names="/" tstamps="/"/>
      <tstamp>60538AA4</tstamp>
    </comp>
    <comp ref="R3">
      <value>90.9R</value>
      <footprint>Resistor_SMD:R_0402_1005Metric</footprint>
      <datasheet>https://www.vishay.com/docs/28773/crcwce3.pdf</datasheet>
      <fields>
        <field name="Description">0402\600WIND,90.9 Ohms,1%</field>
        <field name="Part Number">CRCW040290R9FKEDC</field>
        <field name="Tolerance">1%</field>
      </fields>
      <libsource lib="Device" part="R_Small" description="Resistor, small symbol"/>
      <sheetpath names="/" tstamps="/"/>
      <tstamp>605398E9</tstamp>
    </comp>
    <comp ref="C16">
      <value>820pF</value>
      <footprint>Capacitor_SMD:C_0805_2012Metric</footprint>
      <datasheet>https://www.murata.com/-/media/webrenewal/support/library/catalog/products/capacitor/ceramiccapacitor/c02e.ashx?la=en-us&amp;cvid=20210120024548000000</datasheet>
      <fields>
        <field name="Description">CAP CER 820PF 50V X7R 0402</field>
        <field name="Part Number">GRM155R71H821K</field>
        <field name="Tolerance">10%</field>
        <field name="Voltage">50V</field>
      </fields>
      <libsource lib="Device" part="C_Small" description="Unpolarized capacitor, small symbol"/>
      <sheetpath names="/" tstamps="/"/>
      <tstamp>6057E52A</tstamp>
    </comp>
    <comp ref="U1">
      <value>SN74LV07ADR</value>
      <footprint>Package_SO:TSSOP-14_4.4x5mm_P0.65mm</footprint>
      <datasheet>https://assets.nexperia.com/documents/data-sheet/74LV07A.pdf</datasheet>
      <fields>
        <field name="Description">IC BUF NON-INVERT 5.5V 14SOIC</field>
        <field name="Part Number">SN74LV07ADR</field>
      </fields>
      <libsource lib="74xx" part="74LV07A" description="Hex Inverter"/>
      <sheetpath names="/" tstamps="/"/>
      <tstamp>605DB175</tstamp>
    </comp>
    <comp ref="R7">
      <value>open</value>
      <footprint>Resistor_SMD:R_0402_1005Metric</footprint>
      <datasheet>https://www.vishay.com/docs/20008/dcrcw.pdf</datasheet>
      <fields>
        <field name="Description">RES SMD 0 OHM JUMPER 1/16W 0402</field>
        <field name="Part Number">CRCW04020000ZSTD</field>
        <field name="Tolerance">1%</field>
      </fields>
      <libsource lib="Device" part="R_Small" description="Resistor, small symbol"/>
      <sheetpath names="/" tstamps="/"/>
      <tstamp>605EBC7F</tstamp>
    </comp>
    <comp ref="R1">
      <value>5.1K</value>
      <footprint>Resistor_SMD:R_0402_1005Metric</footprint>
      <datasheet>https://www.vishay.com/docs/28773/crcwce3.pdf</datasheet>
      <fields>
        <field name="Description">RES 5.1K OHM 1% 1/16W 0402</field>
        <field name="Part Number">CRCW04025K10FKEDC</field>
        <field name="Tolerance">1%</field>
      </fields>
      <libsource lib="Device" part="R_Small" description="Resistor, small symbol"/>
      <sheetpath names="/" tstamps="/"/>
      <tstamp>6060ADAE</tstamp>
    </comp>
    <comp ref="R11">
      <value>open</value>
      <footprint>Resistor_SMD:R_0402_1005Metric</footprint>
      <datasheet>https://www.vishay.com/docs/20008/dcrcw.pdf</datasheet>
      <fields>
        <field name="Description">RES SMD 0 OHM JUMPER 1/16W 0402</field>
        <field name="Part Number">CRCW04020000ZSTD</field>
        <field name="Tolerance">1%</field>
      </fields>
      <libsource lib="Device" part="R_Small" description="Resistor, small symbol"/>
      <sheetpath names="/" tstamps="/"/>
      <tstamp>6067A784</tstamp>
    </comp>
    <comp ref="J3">
      <value>MUXOUT</value>
      <footprint>Connector_Coaxial:SMA_Amphenol_132289_EdgeMount</footprint>
      <datasheet>https://s3-us-west-2.amazonaws.com/catsy.582/132289.pdf</datasheet>
      <fields>
        <field name="Description">CONN SMA RCPT STR 50OHM EDGE MNT</field>
        <field name="Part Number">132289</field>
      </fields>
      <libsource lib="Connector" part="Conn_Coaxial" description="coaxial connector (BNC, SMA, SMB, SMC, Cinch/RCA, ...)"/>
      <sheetpath names="/" tstamps="/"/>
      <tstamp>6069A60F</tstamp>
    </comp>
    <comp ref="R18">
      <value>0R</value>
      <footprint>Resistor_SMD:R_0402_1005Metric</footprint>
      <datasheet>https://www.vishay.com/docs/20008/dcrcw.pdf</datasheet>
      <fields>
        <field name="Description">RES SMD 0 OHM JUMPER 1/16W 0402</field>
        <field name="Part Number">CRCW04020000ZSTD</field>
        <field name="Tolerance">1%</field>
      </fields>
      <libsource lib="Device" part="R_Small" description="Resistor, small symbol"/>
      <sheetpath names="/" tstamps="/"/>
      <tstamp>606BC4D1</tstamp>
    </comp>
    <comp ref="R21">
      <value>open</value>
      <footprint>Resistor_SMD:R_0402_1005Metric</footprint>
      <datasheet>https://www.vishay.com/docs/20008/dcrcw.pdf</datasheet>
      <fields>
        <field name="Description">RES SMD 0 OHM JUMPER 1/16W 0402</field>
        <field name="Part Number">CRCW04020000ZSTD</field>
        <field name="Tolerance">1%</field>
      </fields>
      <libsource lib="Device" part="R_Small" description="Resistor, small symbol"/>
      <sheetpath names="/" tstamps="/"/>
      <tstamp>606BD94D</tstamp>
    </comp>
    <comp ref="R20">
      <value>open</value>
      <footprint>Resistor_SMD:R_0402_1005Metric</footprint>
      <datasheet>https://www.vishay.com/docs/20008/dcrcw.pdf</datasheet>
      <fields>
        <field name="Description">RES SMD 0 OHM JUMPER 1/16W 0402</field>
        <field name="Part Number">CRCW04020000ZSTD</field>
        <field name="Tolerance">1%</field>
      </fields>
      <libsource lib="Device" part="R_Small" description="Resistor, small symbol"/>
      <sheetpath names="/" tstamps="/"/>
      <tstamp>606BE04E</tstamp>
    </comp>
    <comp ref="C20">
      <value>open</value>
      <footprint>Capacitor_SMD:C_0402_1005Metric</footprint>
      <datasheet>~</datasheet>
      <libsource lib="Device" part="C_Small" description="Unpolarized capacitor, small symbol"/>
      <sheetpath names="/" tstamps="/"/>
      <tstamp>60710EE9</tstamp>
    </comp>
    <comp ref="J4">
      <value>REFIN</value>
      <footprint>Connector_Coaxial:SMA_Amphenol_132289_EdgeMount</footprint>
      <datasheet>https://s3-us-west-2.amazonaws.com/catsy.582/132289.pdf</datasheet>
      <fields>
        <field name="Description">CONN SMA RCPT STR 50OHM EDGE MNT</field>
        <field name="Part Number">132289</field>
      </fields>
      <libsource lib="Connector" part="Conn_Coaxial" description="coaxial connector (BNC, SMA, SMB, SMC, Cinch/RCA, ...)"/>
      <sheetpath names="/" tstamps="/"/>
      <tstamp>60748DF8</tstamp>
    </comp>
    <comp ref="R19">
      <value>open</value>
      <footprint>Resistor_SMD:R_0402_1005Metric</footprint>
      <datasheet>https://www.vishay.com/docs/20008/dcrcw.pdf</datasheet>
      <fields>
        <field name="Description">RES SMD 0 OHM JUMPER 1/16W 0402</field>
        <field name="Part Number">CRCW04020000ZSTD</field>
        <field name="Tolerance">1%</field>
      </fields>
      <libsource lib="Device" part="R_Small" description="Resistor, small symbol"/>
      <sheetpath names="/" tstamps="/"/>
      <tstamp>6075C65F</tstamp>
    </comp>
    <comp ref="R32">
      <value>5.1K</value>
      <footprint>Resistor_SMD:R_0402_1005Metric</footprint>
      <datasheet>https://www.vishay.com/docs/28773/crcwce3.pdf</datasheet>
      <fields>
        <field name="Description">RES 5.1K OHM 1% 1/16W 0402</field>
        <field name="Part Number">CRCW04025K10FKEDC</field>
        <field name="Tolerance">1%</field>
      </fields>
      <libsource lib="Device" part="R_Small" description="Resistor, small symbol"/>
      <sheetpath names="/" tstamps="/"/>
      <tstamp>608492AC</tstamp>
    </comp>
    <comp ref="D1">
      <value>LED</value>
      <footprint>Diode_SMD:D_0603_1608Metric</footprint>
      <datasheet>https://fscdn.rohm.com/en/products/databook/datasheet/opto/led/chip_mono/sml-d12x8_d13x8-e.pdf</datasheet>
      <fields>
        <field name="Description">LED GREEN DIFFUSED 0603 SMD</field>
        <field name="Part Number">SML-D12P8WT86</field>
      </fields>
      <libsource lib="Device" part="LED" description="Light emitting diode"/>
      <sheetpath names="/" tstamps="/"/>
      <tstamp>60883873</tstamp>
    </comp>
    <comp ref="R33">
      <value>5.1K</value>
      <footprint>Resistor_SMD:R_0402_1005Metric</footprint>
      <datasheet>https://www.vishay.com/docs/28773/crcwce3.pdf</datasheet>
      <fields>
        <field name="Description">RES 5.1K OHM 1% 1/16W 0402</field>
        <field name="Part Number">CRCW04025K10FKEDC</field>
        <field name="Tolerance">1%</field>
      </fields>
      <libsource lib="Device" part="R_Small" description="Resistor, small symbol"/>
      <sheetpath names="/" tstamps="/"/>
      <tstamp>608AC87F</tstamp>
    </comp>
    <comp ref="R26">
      <value>open</value>
      <footprint>Resistor_SMD:R_0402_1005Metric</footprint>
      <datasheet>https://www.vishay.com/docs/20008/dcrcw.pdf</datasheet>
      <fields>
        <field name="Description">RES SMD 0 OHM JUMPER 1/16W 0402</field>
        <field name="Part Number">CRCW04020000ZSTD</field>
        <field name="Tolerance">1%</field>
      </fields>
      <libsource lib="Device" part="R_Small" description="Resistor, small symbol"/>
      <sheetpath names="/" tstamps="/"/>
      <tstamp>608FD11F</tstamp>
    </comp>
    <comp ref="C30">
      <value>10uF</value>
      <footprint>Capacitor_Tantalum_SMD:CP_EIA-6032-20_AVX-F</footprint>
      <datasheet>https://www.mouser.com/datasheet/2/40/taj-776811.pdf</datasheet>
      <fields>
        <field name="Description">Tantalum Capacitors - Solid SMD 16V 10uF 10% 2312 ESR = 2 Ohm</field>
        <field name="Part Number">TAJC106K016SNJV</field>
        <field name="Tolerance">10%</field>
        <field name="Voltage">16V</field>
      </fields>
      <libsource lib="Device" part="C_Polarized_Small" description="Polarized capacitor, small symbol"/>
      <sheetpath names="/" tstamps="/"/>
      <tstamp>611B8552</tstamp>
    </comp>
    <comp ref="C31">
      <value>2.2uF</value>
      <footprint>Capacitor_SMD:C_0201_0603Metric</footprint>
      <datasheet>https://www.murata.com/-/media/webrenewal/support/library/catalog/products/capacitor/ceramiccapacitor/c02e.ashx?la=en-us&amp;cvid=20210120024548000000</datasheet>
      <fields>
        <field name="Description">CAP CER 2.2UF 10V X5R 0201</field>
        <field name="Part Number">GRM033R61A225K</field>
        <field name="Tolerance">10%</field>
        <field name="Voltage">10V</field>
      </fields>
      <libsource lib="Device" part="C_Small" description="Unpolarized capacitor, small symbol"/>
      <sheetpath names="/" tstamps="/"/>
      <tstamp>611DBCE3</tstamp>
    </comp>
    <comp ref="TP5">
      <value>VTUNE</value>
      <footprint>TestPoint:TestPoint_Pad_1.0x1.0mm</footprint>
      <datasheet>~</datasheet>
      <libsource lib="Connector" part="TestPoint" description="test point"/>
      <sheetpath names="/" tstamps="/"/>
      <tstamp>6120F052</tstamp>
    </comp>
    <comp ref="TP4">
      <value>LD</value>
      <footprint>TestPoint:TestPoint_Pad_1.0x1.0mm</footprint>
      <datasheet>~</datasheet>
      <libsource lib="Connector" part="TestPoint" description="test point"/>
      <sheetpath names="/" tstamps="/"/>
      <tstamp>61252060</tstamp>
    </comp>
    <comp ref="TP2">
      <value>MUX_OUT</value>
      <footprint>TestPoint:TestPoint_Pad_1.0x1.0mm</footprint>
      <datasheet>~</datasheet>
      <libsource lib="Connector" part="TestPoint" description="test point"/>
      <sheetpath names="/" tstamps="/"/>
      <tstamp>6129B681</tstamp>
    </comp>
    <comp ref="TP1">
      <value>TestPoint</value>
      <footprint>TestPoint:TestPoint_Pad_1.0x1.0mm</footprint>
      <datasheet>~</datasheet>
      <libsource lib="Connector" part="TestPoint" description="test point"/>
      <sheetpath names="/" tstamps="/"/>
      <tstamp>612BFC07</tstamp>
    </comp>
    <comp ref="TP3">
      <value>RF_EN</value>
      <footprint>TestPoint:TestPoint_Pad_1.0x1.0mm</footprint>
      <datasheet>~</datasheet>
      <libsource lib="Connector" part="TestPoint" description="test point"/>
      <sheetpath names="/" tstamps="/"/>
      <tstamp>6127743D</tstamp>
    </comp>
    <comp ref="J8">
      <value>BMI-S-205</value>
      <footprint>RF_Shielding:Laird_Technologies_BMI-S-205-F_38.10x25.40mm</footprint>
      <datasheet>~</datasheet>
      <libsource lib="Device" part="RFShield_TwoPieces" description="Two-piece EMI RF shielding cabinet"/>
      <sheetpath names="/" tstamps="/"/>
      <tstamp>61283278</tstamp>
    </comp>
    <comp ref="J7">
      <value>Conn_02x06_Odd_Even</value>
      <footprint>Connector_PinHeader_2.54mm:PinHeader_2x06_P2.54mm_Vertical</footprint>
      <datasheet>~</datasheet>
      <libsource lib="Connector_Generic" part="Conn_02x06_Odd_Even" description="Generic connector, double row, 02x06, odd/even pin numbering scheme (row 1 odd numbers, row 2 even numbers), script generated (kicad-library-utils/schlib/autogen/connector/)"/>
      <sheetpath names="/" tstamps="/"/>
      <tstamp>6128DE98</tstamp>
    </comp>
    <comp ref="R8">
      <value>240R</value>
      <footprint>Resistor_SMD:R_0402_1005Metric</footprint>
      <datasheet>https://www.vishay.com/docs/20035/dcrcwe3.pdf</datasheet>
      <fields>
        <field name="Description">RES SMD 240 OHM 5% 1/16W 0402</field>
        <field name="Part Number">CRCW0402240RJNED</field>
        <field name="Tolerance">5%</field>
      </fields>
      <libsource lib="Device" part="R_Small" description="Resistor, small symbol"/>
      <sheetpath names="/" tstamps="/"/>
      <tstamp>60565C44</tstamp>
    </comp>
    <comp ref="C9">
      <value>0.01uF</value>
      <footprint>Capacitor_SMD:C_0402_1005Metric</footprint>
      <datasheet>https://www.murata.com/-/media/webrenewal/support/library/catalog/products/capacitor/ceramiccapacitor/c02e.ashx?la=en-us&amp;cvid=20210120024548000000</datasheet>
      <fields>
        <field name="Description">CAP CER 10000PF 16V X7R 0402</field>
        <field name="Part Number">GRM155R71C103K</field>
        <field name="Tolerance">10%</field>
        <field name="Voltage">16V</field>
      </fields>
      <libsource lib="Device" part="C_Small" description="Unpolarized capacitor, small symbol"/>
      <sheetpath names="/" tstamps="/"/>
      <tstamp>60224CAD</tstamp>
    </comp>
    <comp ref="C7">
      <value>100pF</value>
      <footprint>Capacitor_SMD:C_0402_1005Metric</footprint>
      <datasheet>https://product.tdk.com/en/system/files?file=dam/doc/product/capacitor/ceramic/mlcc/catalog/mlcc_commercial_general_en.pdf</datasheet>
      <fields>
        <field name="Description">CAP CER 100PF 50V C0G 0402</field>
        <field name="Part Number">C1005C0G1H101K</field>
        <field name="Tolerance">5%</field>
        <field name="Voltage">50V</field>
      </fields>
      <libsource lib="Device" part="C_Small" description="Unpolarized capacitor, small symbol"/>
      <sheetpath names="/" tstamps="/"/>
      <tstamp>602246D9</tstamp>
    </comp>
    <comp ref="C4">
      <value>0.01uF</value>
      <footprint>Capacitor_SMD:C_0402_1005Metric</footprint>
      <datasheet>https://www.murata.com/-/media/webrenewal/support/library/catalog/products/capacitor/ceramiccapacitor/c02e.ashx?la=en-us&amp;cvid=20210120024548000000</datasheet>
      <fields>
        <field name="Description">CAP CER 10000PF 16V X7R 0402</field>
        <field name="Part Number">GRM155R71C103K</field>
        <field name="Tolerance">10%</field>
        <field name="Voltage">16V</field>
      </fields>
      <libsource lib="Device" part="C_Small" description="Unpolarized capacitor, small symbol"/>
      <sheetpath names="/" tstamps="/"/>
      <tstamp>6130B260</tstamp>
    </comp>
    <comp ref="C2">
      <value>100pF</value>
      <footprint>Capacitor_SMD:C_0402_1005Metric</footprint>
      <datasheet>https://product.tdk.com/en/system/files?file=dam/doc/product/capacitor/ceramic/mlcc/catalog/mlcc_commercial_general_en.pdf</datasheet>
      <fields>
        <field name="Description">CAP CER 100PF 50V C0G 0402</field>
        <field name="Part Number">C1005C0G1H101K</field>
        <field name="Tolerance">5%</field>
        <field name="Voltage">50V</field>
      </fields>
      <libsource lib="Device" part="C_Small" description="Unpolarized capacitor, small symbol"/>
      <sheetpath names="/" tstamps="/"/>
      <tstamp>6130B26A</tstamp>
    </comp>
    <comp ref="TP6">
      <value>CLK</value>
      <footprint>TestPoint:TestPoint_Pad_1.0x1.0mm</footprint>
      <datasheet>~</datasheet>
      <libsource lib="Connector" part="TestPoint" description="test point"/>
      <sheetpath names="/" tstamps="/"/>
      <tstamp>6145F178</tstamp>
    </comp>
    <comp ref="TP7">
      <value>DATA</value>
      <footprint>TestPoint:TestPoint_Pad_1.0x1.0mm</footprint>
      <datasheet>~</datasheet>
      <libsource lib="Connector" part="TestPoint" description="test point"/>
      <sheetpath names="/" tstamps="/"/>
      <tstamp>61476252</tstamp>
    </comp>
    <comp ref="TP8">
      <value>LE</value>
      <footprint>TestPoint:TestPoint_Pad_1.0x1.0mm</footprint>
      <datasheet>~</datasheet>
      <libsource lib="Connector" part="TestPoint" description="test point"/>
      <sheetpath names="/" tstamps="/"/>
      <tstamp>6148B17D</tstamp>
    </comp>
    <comp ref="TP9">
      <value>CE</value>
      <footprint>TestPoint:TestPoint_Pad_1.0x1.0mm</footprint>
      <datasheet>~</datasheet>
      <libsource lib="Connector" part="TestPoint" description="test point"/>
      <sheetpath names="/" tstamps="/"/>
      <tstamp>614A197A</tstamp>
    </comp>
    <comp ref="TP10">
      <value>SW</value>
      <footprint>TestPoint:TestPoint_Pad_1.0x1.0mm</footprint>
      <datasheet>~</datasheet>
      <libsource lib="Connector" part="TestPoint" description="test point"/>
      <sheetpath names="/" tstamps="/"/>
      <tstamp>614BA8A0</tstamp>
    </comp>
    <comp ref="J9">
      <value>Conn_01x02_Female</value>
      <footprint>Connector_JST:JST_EH_B2B-EH-A_1x02_P2.50mm_Vertical</footprint>
      <datasheet>~</datasheet>
      <libsource lib="Connector" part="Conn_01x02_Female" description="Generic connector, single row, 01x02, script generated (kicad-library-utils/schlib/autogen/connector/)"/>
      <sheetpath names="/" tstamps="/"/>
      <tstamp>613FC185</tstamp>
    </comp>
  </components>
  <libparts>
    <libpart lib="74xx" part="74LV07A">
      <description>Hex Inverter</description>
      <docs>https://assets.nexperia.com/documents/data-sheet/74LV07A.pdf</docs>
      <fields>
        <field name="Reference">U</field>
        <field name="Value">74LV07A</field>
        <field name="Footprint">Package_SO:TSSOP-14_4.4x5mm_P0.65mm</field>
      </fields>
      <pins>
        <pin num="1" name="~" type="input"/>
        <pin num="2" name="~" type="output"/>
        <pin num="3" name="~" type="input"/>
        <pin num="4" name="~" type="output"/>
        <pin num="5" name="~" type="input"/>
        <pin num="6" name="~" type="output"/>
        <pin num="7" name="GND" type="power_in"/>
        <pin num="8" name="~" type="output"/>
        <pin num="9" name="~" type="input"/>
        <pin num="10" name="~" type="output"/>
        <pin num="11" name="~" type="input"/>
        <pin num="12" name="~" type="output"/>
        <pin num="13" name="~" type="input"/>
        <pin num="14" name="VCC" type="power_in"/>
      </pins>
    </libpart>
    <libpart lib="Connector" part="Conn_01x02_Female">
      <description>Generic connector, single row, 01x02, script generated (kicad-library-utils/schlib/autogen/connector/)</description>
      <docs>~</docs>
      <footprints>
        <fp>Connector*:*_1x??_*</fp>
      </footprints>
      <fields>
        <field name="Reference">J</field>
        <field name="Value">Conn_01x02_Female</field>
      </fields>
      <pins>
        <pin num="1" name="Pin_1" type="passive"/>
        <pin num="2" name="Pin_2" type="passive"/>
      </pins>
    </libpart>
    <libpart lib="Connector" part="Conn_Coaxial">
      <description>coaxial connector (BNC, SMA, SMB, SMC, Cinch/RCA, ...)</description>
      <docs> ~</docs>
      <footprints>
        <fp>*BNC*</fp>
        <fp>*SMA*</fp>
        <fp>*SMB*</fp>
        <fp>*SMC*</fp>
        <fp>*Cinch*</fp>
      </footprints>
      <fields>
        <field name="Reference">J</field>
        <field name="Value">Conn_Coaxial</field>
      </fields>
      <pins>
        <pin num="1" name="In" type="passive"/>
        <pin num="2" name="Ext" type="passive"/>
      </pins>
    </libpart>
    <libpart lib="Connector" part="TestPoint">
      <description>test point</description>
      <docs>~</docs>
      <footprints>
        <fp>Pin*</fp>
        <fp>Test*</fp>
      </footprints>
      <fields>
        <field name="Reference">TP</field>
        <field name="Value">TestPoint</field>
      </fields>
      <pins>
        <pin num="1" name="1" type="passive"/>
      </pins>
    </libpart>
    <libpart lib="Connector_Generic" part="Conn_02x06_Odd_Even">
      <description>Generic connector, double row, 02x06, odd/even pin numbering scheme (row 1 odd numbers, row 2 even numbers), script generated (kicad-library-utils/schlib/autogen/connector/)</description>
      <docs>~</docs>
      <footprints>
        <fp>Connector*:*_2x??_*</fp>
      </footprints>
      <fields>
        <field name="Reference">J</field>
        <field name="Value">Conn_02x06_Odd_Even</field>
      </fields>
      <pins>
        <pin num="1" name="Pin_1" type="passive"/>
        <pin num="2" name="Pin_2" type="passive"/>
        <pin num="3" name="Pin_3" type="passive"/>
        <pin num="4" name="Pin_4" type="passive"/>
        <pin num="5" name="Pin_5" type="passive"/>
        <pin num="6" name="Pin_6" type="passive"/>
        <pin num="7" name="Pin_7" type="passive"/>
        <pin num="8" name="Pin_8" type="passive"/>
        <pin num="9" name="Pin_9" type="passive"/>
        <pin num="10" name="Pin_10" type="passive"/>
        <pin num="11" name="Pin_11" type="passive"/>
        <pin num="12" name="Pin_12" type="passive"/>
      </pins>
    </libpart>
    <libpart lib="Device" part="C_Polarized_Small">
      <description>Polarized capacitor, small symbol</description>
      <docs>~</docs>
      <footprints>
        <fp>CP_*</fp>
      </footprints>
      <fields>
        <field name="Reference">C</field>
        <field name="Value">C_Polarized_Small</field>
      </fields>
      <pins>
        <pin num="1" name="~" type="passive"/>
        <pin num="2" name="~" type="passive"/>
      </pins>
    </libpart>
    <libpart lib="Device" part="C_Small">
      <description>Unpolarized capacitor, small symbol</description>
      <docs>~</docs>
      <footprints>
        <fp>C_*</fp>
      </footprints>
      <fields>
        <field name="Reference">C</field>
        <field name="Value">C_Small</field>
      </fields>
      <pins>
        <pin num="1" name="~" type="passive"/>
        <pin num="2" name="~" type="passive"/>
      </pins>
    </libpart>
    <libpart lib="Device" part="LED">
      <description>Light emitting diode</description>
      <docs>~</docs>
      <footprints>
        <fp>LED*</fp>
        <fp>LED_SMD:*</fp>
        <fp>LED_THT:*</fp>
      </footprints>
      <fields>
        <field name="Reference">D</field>
        <field name="Value">LED</field>
      </fields>
      <pins>
        <pin num="1" name="K" type="passive"/>
        <pin num="2" name="A" type="passive"/>
      </pins>
    </libpart>
    <libpart lib="Device" part="RFShield_TwoPieces">
      <description>Two-piece EMI RF shielding cabinet</description>
      <docs>~</docs>
      <fields>
        <field name="Reference">J</field>
        <field name="Value">RFShield_TwoPieces</field>
      </fields>
      <pins>
        <pin num="1" name="Shield" type="passive"/>
      </pins>
    </libpart>
    <libpart lib="Device" part="R_Small">
      <description>Resistor, small symbol</description>
      <docs>~</docs>
      <footprints>
        <fp>R_*</fp>
      </footprints>
      <fields>
        <field name="Reference">R</field>
        <field name="Value">R_Small</field>
      </fields>
      <pins>
        <pin num="1" name="~" type="passive"/>
        <pin num="2" name="~" type="passive"/>
      </pins>
    </libpart>
    <libpart lib="Regulator_Linear" part="MAX8559">
      <description>Dual, 300mA, Low-Noise Linear Regulator with Independent Shutdown</description>
      <docs>https://datasheets.maximintegrated.com/en/ds/MAX8559.pdf</docs>
      <fields>
        <field name="Reference">U</field>
        <field name="Value">MAX8559</field>
      </fields>
      <pins>
        <pin num="1" name="INA" type="power_in"/>
        <pin num="2" name="~SHDNA~" type="input"/>
        <pin num="3" name="~SHDNB~" type="input"/>
        <pin num="4" name="INB" type="power_in"/>
        <pin num="5" name="OUTB" type="power_out"/>
        <pin num="6" name="GND" type="power_in"/>
        <pin num="7" name="BP" type="passive"/>
        <pin num="8" name="OUTA" type="power_out"/>
        <pin num="9" name="EP" type="power_in"/>
      </pins>
    </libpart>
    <libpart lib="Timer_PLL" part="MAX2870">
      <description>23.5MHz to 6000MHz Fractional/Integer-N Synthesizer/VCO</description>
      <docs>https://datasheets.maximintegrated.com/en/ds/MAX2870.pdf</docs>
      <fields>
        <field name="Reference">U</field>
        <field name="Value">MAX2870</field>
        <field name="Footprint">Package_DFN_QFN:TQFN-32-1EP_5x5mm_P0.5mm_EP3.1x3.1mm</field>
      </fields>
      <pins>
        <pin num="1" name="CLK" type="input"/>
        <pin num="2" name="DATA" type="input"/>
        <pin num="3" name="LE" type="input"/>
        <pin num="4" name="CE" type="input"/>
        <pin num="5" name="SW" type="BiDi"/>
        <pin num="6" name="VCC_CP" type="passive"/>
        <pin num="7" name="CP_OUT" type="passive"/>
        <pin num="8" name="GND_CP" type="power_in"/>
        <pin num="9" name="GND_PLL" type="power_in"/>
        <pin num="10" name="VCC_PL" type="power_in"/>
        <pin num="11" name="GND_RF" type="power_in"/>
        <pin num="12" name="RFOUTA_P" type="output"/>
        <pin num="13" name="RFOUTA_N" type="output"/>
        <pin num="14" name="RFOUTB_P" type="output"/>
        <pin num="15" name="RFOUTB_N" type="output"/>
        <pin num="16" name="VCC_RF" type="power_in"/>
        <pin num="17" name="VCC_VCO" type="power_in"/>
        <pin num="18" name="GND_VCO" type="power_in"/>
        <pin num="19" name="NOISE_FLIT" type="passive"/>
        <pin num="20" name="TUNE" type="input"/>
        <pin num="21" name="GND_TUNE" type="power_in"/>
        <pin num="22" name="RSET" type="input"/>
        <pin num="23" name="BIAS_FLIT" type="power_in"/>
        <pin num="24" name="REG" type="passive"/>
        <pin num="25" name="LD" type="input"/>
        <pin num="26" name="RFOUT_EN" type="input"/>
        <pin num="27" name="GND_DIG" type="power_in"/>
        <pin num="28" name="VCC_DIG" type="power_in"/>
        <pin num="29" name="RF_IN" type="input"/>
        <pin num="30" name="MUX_OUT" type="output"/>
        <pin num="31" name="GND_SD" type="power_in"/>
        <pin num="32" name="VDD_SD" type="power_in"/>
      </pins>
    </libpart>
  </libparts>
  <libraries>
    <library logical="74xx">
      <uri>C:\Program Files\KiCad\share\kicad\library/74xx.lib</uri>
    </library>
    <library logical="Connector">
      <uri>C:\Program Files\KiCad\share\kicad\library/Connector.lib</uri>
    </library>
    <library logical="Connector_Generic">
      <uri>C:\Program Files\KiCad\share\kicad\library/Connector_Generic.lib</uri>
    </library>
    <library logical="Device">
      <uri>C:\Program Files\KiCad\share\kicad\library/Device.lib</uri>
    </library>
    <library logical="Regulator_Linear">
      <uri>C:\Program Files\KiCad\share\kicad\library/Regulator_Linear.lib</uri>
    </library>
    <library logical="Timer_PLL">
      <uri>C:\Program Files\KiCad\share\kicad\library/Timer_PLL.lib</uri>
    </library>
  </libraries>
  <nets>
    <net code="1" name="GND">
      <node ref="C27" pin="1"/>
      <node ref="U2" pin="9"/>
      <node ref="U2" pin="8"/>
      <node ref="C17" pin="2"/>
      <node ref="U2" pin="31"/>
      <node ref="U2" pin="27"/>
      <node ref="C29" pin="1"/>
      <node ref="C28" pin="1"/>
      <node ref="R29" pin="1"/>
      <node ref="C13" pin="1"/>
      <node ref="C1" pin="1"/>
      <node ref="C3" pin="1"/>
      <node ref="C11" pin="2"/>
      <node ref="C18" pin="2"/>
      <node ref="C26" pin="2"/>
      <node ref="J8" pin="1"/>
      <node ref="J9" pin="2"/>
      <node ref="C9" pin="1"/>
      <node ref="C2" pin="1"/>
      <node ref="C4" pin="1"/>
      <node ref="U1" pin="7"/>
      <node ref="R10" pin="1"/>
      <node ref="R15" pin="1"/>
      <node ref="R9" pin="1"/>
      <node ref="C19" pin="2"/>
      <node ref="C34" pin="2"/>
      <node ref="C32" pin="1"/>
      <node ref="R31" pin="1"/>
      <node ref="R24" pin="1"/>
      <node ref="R30" pin="1"/>
      <node ref="R25" pin="1"/>
      <node ref="R14" pin="1"/>
      <node ref="J6" pin="2"/>
      <node ref="J5" pin="2"/>
      <node ref="U3" pin="9"/>
      <node ref="U3" pin="6"/>
      <node ref="C14" pin="2"/>
      <node ref="C8" pin="1"/>
      <node ref="C6" pin="1"/>
      <node ref="U2" pin="21"/>
      <node ref="U2" pin="18"/>
      <node ref="U2" pin="11"/>
      <node ref="C15" pin="2"/>
      <node ref="C12" pin="2"/>
      <node ref="C38" pin="2"/>
      <node ref="C33" pin="2"/>
      <node ref="C36" pin="2"/>
      <node ref="C7" pin="1"/>
      <node ref="D3" pin="1"/>
      <node ref="J2" pin="2"/>
      <node ref="J1" pin="2"/>
      <node ref="D2" pin="1"/>
      <node ref="R3" pin="2"/>
      <node ref="C10" pin="1"/>
      <node ref="D1" pin="1"/>
      <node ref="C31" pin="2"/>
      <node ref="C30" pin="2"/>
      <node ref="C16" pin="1"/>
      <node ref="C35" pin="2"/>
      <node ref="C37" pin="2"/>
      <node ref="R19" pin="1"/>
      <node ref="J3" pin="2"/>
      <node ref="J4" pin="2"/>
      <node ref="R20" pin="1"/>
      <node ref="R21" pin="1"/>
    </net>
    <net code="2" name="Net-(C20-Pad1)">
      <node ref="R20" pin="2"/>
      <node ref="J4" pin="1"/>
      <node ref="C20" pin="1"/>
      <node ref="R19" pin="2"/>
      <node ref="R18" pin="1"/>
    </net>
    <net code="3" name="Net-(C20-Pad2)">
      <node ref="R18" pin="2"/>
      <node ref="R21" pin="2"/>
      <node ref="C21" pin="2"/>
      <node ref="C20" pin="2"/>
    </net>
    <net code="4" name="Net-(R26-Pad2)">
      <node ref="U1" pin="5"/>
      <node ref="U1" pin="1"/>
      <node ref="U2" pin="25"/>
      <node ref="TP4" pin="1"/>
      <node ref="R26" pin="2"/>
    </net>
    <net code="5" name="VCC_PLL">
      <node ref="C8" pin="2"/>
      <node ref="R37" pin="1"/>
      <node ref="U2" pin="32"/>
      <node ref="C3" pin="2"/>
      <node ref="C1" pin="2"/>
      <node ref="R1" pin="1"/>
      <node ref="C6" pin="2"/>
      <node ref="R26" pin="1"/>
      <node ref="C17" pin="1"/>
      <node ref="U2" pin="6"/>
      <node ref="R11" pin="1"/>
      <node ref="C34" pin="1"/>
      <node ref="U2" pin="28"/>
      <node ref="C15" pin="1"/>
      <node ref="R33" pin="1"/>
      <node ref="U2" pin="10"/>
      <node ref="C18" pin="1"/>
      <node ref="U1" pin="14"/>
      <node ref="C38" pin="1"/>
      <node ref="C14" pin="1"/>
      <node ref="U3" pin="5"/>
      <node ref="C36" pin="1"/>
      <node ref="R32" pin="1"/>
    </net>
    <net code="6" name="LD">
      <node ref="U1" pin="2"/>
      <node ref="R32" pin="2"/>
      <node ref="J7" pin="1"/>
    </net>
    <net code="7" name="Net-(D1-Pad2)">
      <node ref="R33" pin="2"/>
      <node ref="D1" pin="2"/>
      <node ref="U1" pin="6"/>
    </net>
    <net code="8" name="Net-(C5-Pad1)">
      <node ref="R2" pin="1"/>
      <node ref="C5" pin="1"/>
    </net>
    <net code="9" name="Net-(D2-Pad2)">
      <node ref="R36" pin="2"/>
      <node ref="D2" pin="2"/>
    </net>
    <net code="10" name="MAX2870_MUX">
      <node ref="J7" pin="3"/>
      <node ref="R1" pin="2"/>
      <node ref="U1" pin="4"/>
    </net>
    <net code="11" name="Net-(R7-Pad2)">
      <node ref="U1" pin="8"/>
      <node ref="R7" pin="2"/>
    </net>
    <net code="12" name="Net-(J3-Pad1)">
      <node ref="TP2" pin="1"/>
      <node ref="J3" pin="1"/>
      <node ref="U1" pin="3"/>
      <node ref="U2" pin="30"/>
      <node ref="R7" pin="1"/>
      <node ref="R11" pin="2"/>
    </net>
    <net code="13" name="Net-(C10-Pad2)">
      <node ref="C10" pin="2"/>
      <node ref="U2" pin="7"/>
      <node ref="C5" pin="2"/>
      <node ref="R8" pin="2"/>
    </net>
    <net code="14" name="VCC_VCO">
      <node ref="U3" pin="8"/>
      <node ref="U2" pin="16"/>
      <node ref="U2" pin="17"/>
      <node ref="C9" pin="2"/>
      <node ref="C2" pin="2"/>
      <node ref="C7" pin="2"/>
      <node ref="C4" pin="2"/>
      <node ref="R36" pin="1"/>
      <node ref="C26" pin="1"/>
      <node ref="R22" pin="1"/>
      <node ref="R23" pin="1"/>
      <node ref="C37" pin="1"/>
      <node ref="C33" pin="1"/>
      <node ref="C35" pin="1"/>
    </net>
    <net code="15" name="Net-(C11-Pad1)">
      <node ref="R6" pin="1"/>
      <node ref="TP8" pin="1"/>
      <node ref="U2" pin="3"/>
      <node ref="C11" pin="1"/>
    </net>
    <net code="16" name="Net-(R2-Pad2)">
      <node ref="U2" pin="5"/>
      <node ref="R3" pin="1"/>
      <node ref="TP10" pin="1"/>
      <node ref="R2" pin="2"/>
    </net>
    <net code="17" name="RF_EN">
      <node ref="U2" pin="26"/>
      <node ref="TP3" pin="1"/>
      <node ref="J7" pin="10"/>
    </net>
    <net code="18" name="Net-(J7-Pad11)">
      <node ref="J7" pin="11"/>
    </net>
    <net code="19" name="MAX2870_CLK">
      <node ref="J7" pin="2"/>
      <node ref="R4" pin="2"/>
    </net>
    <net code="20" name="MAX2870_DATA">
      <node ref="J7" pin="4"/>
      <node ref="R5" pin="2"/>
    </net>
    <net code="21" name="Net-(J7-Pad5)">
      <node ref="J7" pin="5"/>
    </net>
    <net code="22" name="MAX2870_LE">
      <node ref="J7" pin="6"/>
      <node ref="R6" pin="2"/>
    </net>
    <net code="23" name="Net-(C16-Pad2)">
      <node ref="C16" pin="2"/>
      <node ref="TP5" pin="1"/>
      <node ref="R8" pin="1"/>
      <node ref="U2" pin="20"/>
    </net>
    <net code="24" name="Net-(J7-Pad7)">
      <node ref="J7" pin="7"/>
    </net>
    <net code="25" name="PHASE_ADJ">
      <node ref="U1" pin="9"/>
      <node ref="J7" pin="12"/>
      <node ref="TP1" pin="1"/>
    </net>
    <net code="26" name="MAX2870_CE">
      <node ref="U2" pin="4"/>
      <node ref="TP9" pin="1"/>
      <node ref="J7" pin="8"/>
    </net>
    <net code="27" name="Net-(J7-Pad9)">
      <node ref="J7" pin="9"/>
    </net>
    <net code="28" name="Net-(R29-Pad2)">
      <node ref="R29" pin="2"/>
      <node ref="U2" pin="22"/>
    </net>
    <net code="29" name="Net-(C28-Pad2)">
      <node ref="C28" pin="2"/>
      <node ref="U2" pin="23"/>
    </net>
    <net code="30" name="Net-(C29-Pad2)">
      <node ref="C29" pin="2"/>
      <node ref="U2" pin="19"/>
    </net>
    <net code="31" name="Net-(C27-Pad2)">
      <node ref="C27" pin="2"/>
      <node ref="U2" pin="24"/>
    </net>
    <net code="32" name="Net-(C24-Pad2)">
      <node ref="U2" pin="14"/>
      <node ref="C24" pin="2"/>
      <node ref="R23" pin="2"/>
    </net>
    <net code="33" name="Net-(C25-Pad2)">
      <node ref="U2" pin="15"/>
      <node ref="C25" pin="2"/>
      <node ref="R22" pin="2"/>
    </net>
    <net code="34" name="Net-(C22-Pad1)">
      <node ref="C22" pin="1"/>
      <node ref="R14" pin="2"/>
      <node ref="R12" pin="1"/>
    </net>
    <net code="35" name="Net-(C22-Pad2)">
      <node ref="R16" pin="1"/>
      <node ref="C22" pin="2"/>
      <node ref="U2" pin="12"/>
    </net>
    <net code="36" name="Net-(C23-Pad1)">
      <node ref="R13" pin="1"/>
      <node ref="C23" pin="1"/>
      <node ref="R15" pin="2"/>
    </net>
    <net code="37" name="Net-(C24-Pad1)">
      <node ref="C24" pin="1"/>
      <node ref="R28" pin="2"/>
      <node ref="R25" pin="2"/>
    </net>
    <net code="38" name="Net-(C12-Pad1)">
      <node ref="R5" pin="1"/>
      <node ref="TP7" pin="1"/>
      <node ref="U2" pin="2"/>
      <node ref="C12" pin="1"/>
    </net>
    <net code="39" name="Net-(C13-Pad2)">
      <node ref="U2" pin="1"/>
      <node ref="R4" pin="1"/>
      <node ref="C13" pin="2"/>
      <node ref="TP6" pin="1"/>
    </net>
    <net code="40" name="Net-(C21-Pad1)">
      <node ref="U2" pin="29"/>
      <node ref="C21" pin="1"/>
    </net>
    <net code="41" name="Net-(C19-Pad1)">
      <node ref="R16" pin="2"/>
      <node ref="C19" pin="1"/>
      <node ref="R17" pin="2"/>
    </net>
    <net code="42" name="Net-(R34-Pad1)">
      <node ref="R34" pin="1"/>
      <node ref="U3" pin="2"/>
    </net>
    <net code="43" name="+5V">
      <node ref="U3" pin="1"/>
      <node ref="J9" pin="1"/>
      <node ref="C30" pin="1"/>
      <node ref="C31" pin="1"/>
      <node ref="U3" pin="4"/>
      <node ref="R34" pin="2"/>
      <node ref="R35" pin="2"/>
    </net>
    <net code="44" name="Net-(R35-Pad1)">
      <node ref="U3" pin="3"/>
      <node ref="R35" pin="1"/>
    </net>
    <net code="45" name="Net-(J6-Pad1)">
      <node ref="R31" pin="2"/>
      <node ref="J6" pin="1"/>
      <node ref="R28" pin="1"/>
    </net>
    <net code="46" name="Net-(D3-Pad2)">
      <node ref="D3" pin="2"/>
      <node ref="R37" pin="2"/>
    </net>
    <net code="47" name="Net-(C32-Pad2)">
      <node ref="U3" pin="7"/>
      <node ref="C32" pin="2"/>
    </net>
    <net code="48" name="Net-(J1-Pad1)">
      <node ref="J1" pin="1"/>
      <node ref="R9" pin="2"/>
      <node ref="R12" pin="2"/>
    </net>
    <net code="49" name="Net-(J2-Pad1)">
      <node ref="J2" pin="1"/>
      <node ref="R10" pin="2"/>
      <node ref="R13" pin="2"/>
    </net>
    <net code="50" name="Net-(C23-Pad2)">
      <node ref="C23" pin="2"/>
      <node ref="U2" pin="13"/>
      <node ref="R17" pin="1"/>
    </net>
    <net code="51" name="Net-(J5-Pad1)">
      <node ref="J5" pin="1"/>
      <node ref="R30" pin="2"/>
      <node ref="R27" pin="1"/>
    </net>
    <net code="52" name="Net-(C25-Pad1)">
      <node ref="R24" pin="2"/>
      <node ref="R27" pin="2"/>
      <node ref="C25" pin="1"/>
    </net>
  </nets>
</export>
